[
  {
    "ID": 1002,
    "Ids": 0.8,
    "Ids1": 0,
    "notes": "英雄返还经验占比"
  },
  {
    "ID": 1003,
    "Ids": 0,
    "Ids1": "12:50000|10001:15",
    "notes": "解锁2阶职业"
  },
  {
    "ID": 1004,
    "Ids": 0,
    "Ids1": "12:50000|10002:50",
    "notes": "解锁3阶职业"
  },
  {
    "ID": 1005,
    "Ids": 0,
    "Ids1": "12:50000",
    "notes": "重复转职消耗"
  },
  {
    "ID": 1006,
    "Ids": 0,
    "Ids1": "20001|20002|20003|20004",
    "notes": "英雄升级消耗道具"
  },
  {
    "ID": 1007,
    "Ids": 200,
    "Ids1": 0,
    "notes": "英雄重置钻石消耗"
  },
  {
    "ID": 1008,
    "Ids": 900000,
    "Ids1": 0,
    "notes": "新手召唤多少次消失"
  },
  {
    "ID": 1009,
    "Ids": 0,
    "Ids1": 0.2,
    "notes": "职业克制系数, 伤害增加20%"
  },
  {
    "ID": 1010,
    "Ids": 0.8,
    "Ids1": 0,
    "notes": "分解装备强化材料返还系数（千分比）"
  },
  {
    "ID": 1011,
    "Ids": 1,
    "Ids1": 300,
    "notes": "体力回复值，体力恢复时间（秒）"
  },
  {
    "ID": 1012,
    "Ids": 0,
    "Ids1": 60,
    "notes": "升级提升体力上限，初始体力上限"
  },
  {
    "ID": 1013,
    "Ids": 120,
    "Ids1": "50|50|100|200",
    "notes": "购买获得的体力值，对应次数购买所需钻石（购买完最后一档后，本日无法继续购买）"
  },
  {
    "ID": 1014,
    "Ids": 0,
    "Ids1": 60,
    "notes": "体力最大上限"
  },
  {
    "ID": 1015,
    "Ids": 0,
    "Ids1": 0,
    "notes": "升级提供额外体力恢复"
  },
  {
    "ID": 1100,
    "Ids": 0,
    "Ids1": "1:8|8:2|2:1",
    "notes": "步兵＞野兽＞骑兵＞步兵"
  },
  {
    "ID": 1101,
    "Ids": 0,
    "Ids1": "3:4|4:5|5:3",
    "notes": "弓兵＞飞兵＞魔法＞弓兵"
  },
  {
    "ID": 1102,
    "Ids": 0,
    "Ids1": "6:7",
    "notes": "牧师＞魔物"
  },
  {
    "ID": 1103,
    "Ids": 0,
    "Ids1": "11001|13001",
    "notes": "默认上阵英雄"
  },
  {
    "ID": 1104,
    "Ids": 1,
    "Ids1": 0,
    "notes": "1体力=1账号经验"
  },
  {
    "ID": 1105,
    "Ids": 0,
    "Ids1": 1,
    "notes": "科技点初始默认拥有点数"
  },
  {
    "ID": 1106,
    "Ids": 1200,
    "Ids1": 0,
    "notes": "小兵脱离英雄的最大距离，超过则小兵返回到英雄身边"
  },
  {
    "ID": 1107,
    "Ids": 8001,
    "Ids1": 6001,
    "notes": "默认上阵建筑（IDS基础塔，IDS1高级塔）"
  },
  {
    "ID": 1108,
    "Ids": 0,
    "Ids1": "1:11|2:11|3:11|4:21|5:31|6:41",
    "notes": "防御塔布阵界面，可配置的槽根据关卡解锁   位置|解锁关卡"
  },
  {
    "ID": 1109,
    "Ids": 0,
    "Ids1": "5|2",
    "notes": "伤害浮动(第一个正负基础值，第二个正负百分比）"
  },
  {
    "ID": 1110,
    "Ids": 0,
    "Ids1": "世界各地已经被哥布林大军占领，人类只剩下最后一座城池。",
    "notes": "新手剧情1文本"
  },
  {
    "ID": 1111,
    "Ids": 0,
    "Ids1": "老国王将王位传给王子，王子临危受命。",
    "notes": "新手剧情2文本"
  },
  {
    "ID": 1112,
    "Ids": 0,
    "Ids1": "王子继位后不久，哥布林大军发起了对人族的进攻。",
    "notes": "新手剧情3文本"
  },
  {
    "ID": 1113,
    "Ids": 1.5,
    "Ids1": 0,
    "notes": "两倍加速实际效果"
  },
  {
    "ID": 1114,
    "Ids": 21,
    "Ids1": 3,
    "notes": "tap评价"
  },
  {
    "ID": 1115,
    "Ids": 99,
    "Ids1": "关卡达到第13关开启训练营",
    "notes": "士兵训练营功能开启（根据关卡ID解锁）"
  },
  {
    "ID": 1116,
    "Ids": 99,
    "Ids1": "敬请期待",
    "notes": "冒险副本功能开启（根据关卡ID解锁）"
  },
  {
    "ID": 1117,
    "Ids": 2,
    "Ids1": 0,
    "notes": "金币副本限制次数"
  },
  {
    "ID": 1118,
    "Ids": 2,
    "Ids1": 0,
    "notes": "科技副本限制次数"
  },
  {
    "ID": 1119,
    "Ids": 2,
    "Ids1": 0,
    "notes": "装备副本限制次数"
  },
  {
    "ID": 1120,
    "Ids": 0.8,
    "Ids1": 0,
    "notes": "装备分解金币返还数量"
  },
  {
    "ID": 1121,
    "Ids": 99,
    "Ids1": "关卡达到第5关开启铁匠铺",
    "notes": "冒险副本功能开启（根据关卡ID解锁）"
  },
  {
    "ID": 1122,
    "Ids": 0,
    "Ids1": "1:22:2",
    "notes": "日常任务活跃度奖励"
  },
  {
    "ID": 1123,
    "Ids": 2,
    "Ids1": 201,
    "notes": "无尽裂缝关卡挑战次数，关卡id"
  },
  {
    "ID": 1124,
    "Ids": 11,
    "Ids1": 1,
    "notes": "首充入口开启挑战，关卡id，等级"
  },
  {
    "ID": 1125,
    "Ids": 10,
    "Ids1": 0,
    "notes": "竞技场每日挑战次数"
  },
  {
    "ID": 1126,
    "Ids": 5,
    "Ids1": 50,
    "notes": "可购买挑战次数，每次购买消耗的钻石"
  },
  {
    "ID": 1127,
    "Ids": 1000,
    "Ids1": 5,
    "notes": "竞技场初始积分，竞技场获胜基础积分"
  },
  {
    "ID": 1128,
    "Ids": 99,
    "Ids1": "等级达到20级开启竞技场",
    "notes": "竞技场开放等级"
  },
  {
    "ID": 1129,
    "Ids": 99,
    "Ids1": "关卡达到2-5开启无尽裂缝",
    "notes": "无尽裂缝功能开启（根据关卡id解锁）"
  },
  {
    "ID": 1130,
    "Ids": 60,
    "Ids1": 0,
    "notes": "离线挂机每多少秒获得一次收益"
  },
  {
    "ID": 1131,
    "Ids": 100,
    "Ids1": 1,
    "notes": "每多少秒获得金币，ids+ids1*通关关卡数"
  },
  {
    "ID": 1132,
    "Ids": 0.1,
    "Ids1": 0.001,
    "notes": "每多少秒获得钻石，ids+ids1*通关关卡数"
  },
  {
    "ID": 1133,
    "Ids": 0,
    "Ids1": "7200|14400|21600",
    "notes": "挂机时间三个阶段，分别展示，烤鱼，烤鸡，烤大肉腿"
  },
  {
    "ID": 1134,
    "Ids": 0,
    "Ids1": "1:12:5000",
    "notes": "竞技场获胜获得奖励"
  },
  {
    "ID": 1135,
    "Ids": 99,
    "Ids1": 0,
    "notes": "七日签到开放条件【解锁的关卡id】"
  },
  {
    "ID": 1136,
    "Ids": 99,
    "Ids1": 0,
    "notes": "七日送礼开放条件【解锁的关卡id】"
  },
  {
    "ID": 1137,
    "Ids": 99,
    "Ids1": 2,
    "notes": "助力礼包开放条件【解锁关卡id】，限时时间，小时"
  },
  {
    "ID": 1138,
    "Ids": 3,
    "Ids1": 0,
    "notes": "循环boss每日挑战次数"
  },
  {
    "ID": 1139,
    "Ids": 99,
    "Ids1": "等级达到20级开启探险",
    "notes": "循环boss开放等级"
  },
  {
    "ID": 1140,
    "Ids": 0,
    "Ids1": "1:12:5000",
    "notes": "循环BOSS挑战结算奖励"
  },
  {
    "ID": 1141,
    "Ids": 99,
    "Ids1": 168,
    "notes": "战令解锁等级，战令持续时间"
  },
  {
    "ID": 1142,
    "Ids": 3,
    "Ids1": 0,
    "notes": "每日限时礼包触发间隔时间，小时"
  },
  {
    "ID": 1143,
    "Ids": 99,
    "Ids1": 720,
    "notes": "月战令解锁等级，战令持续时间"
  },
  {
    "ID": 2001,
    "Ids": 0,
    "Ids1": "1:1|2:2|3:4|4:6",
    "notes": "装备随机词条数量"
  },
  {
    "ID": 2002,
    "Ids": 0,
    "Ids1": "5:20|15:20|30:20|50:20|75:70",
    "notes": "参与击杀怪物数量：士兵提升属性百分比【取当前等级值，不叠加】"
  },
  {
    "ID": 2003,
    "Ids": 50,
    "Ids1": 0,
    "notes": "开启困难难度"
  },
  {
    "ID": 2004,
    "Ids": 36,
    "Ids1": 0,
    "notes": "1个区域地图区域快数量"
  },
  {
    "ID": 2005,
    "Ids": 0,
    "Ids1": "1:1,2:1,3:20",
    "notes": "出战士兵数量:解锁等级"
  },
  {
    "ID": 2006,
    "Ids": 25,
    "Ids1": "25级开启第3个出战位",
    "notes": "英雄出战解锁"
  }
]