[
  {
    "id": 1,
    "nextid": 2,
    "uiIndex": 2,
    "type": 1,
    "showTip": "通关章节1-1",
    "MissionType": 1,
    "UseNum": 1,
    "UseId": 12,
    "Mission": 101,
    "story1": "开始你的旅程吧，祝你一路顺风。",
    "story2": "恭喜你踏出了第一步，这是你的奖励，希望你能再接再厉！",
    "sound1": "renwu_start_1",
    "sound2": "renwu_end_1",
    "Reward": "1:11:30|1:12:10000|1:22:2|1:10201:2"
  },
  {
    "id": 2,
    "nextid": 3,
    "uiIndex": 2,
    "type": 1,
    "showTip": "1个英雄升级到2级",
    "MissionType": 2,
    "UseNum": 1,
    "UseId": 2,
    "Mission": 108,
    "story1": "升级英雄，提升能力。",
    "story2": "恭喜你，实力又提升一步。",
    "sound1": "renwu_start_3",
    "sound2": "renwu_end_3",
    "Reward": "1:11:30|1:12:10000|1:22:2|1:10010:2"
  },
  {
    "id": 3,
    "nextid": 4,
    "uiIndex": 2,
    "type": 1,
    "showTip": "通关章节1-2",
    "MissionType": 1,
    "UseNum": 1,
    "UseId": 13,
    "Mission": 101,
    "story1": "勇闯难关，祝你一路顺风。",
    "story2": "太棒了，这一关你都轻松通过。",
    "sound1": "renwu_start_4",
    "sound2": "renwu_end_4",
    "Reward": "1:11:30|1:12:10000|1:22:2|1:10201:2"
  },
  {
    "id": 4,
    "nextid": 5,
    "uiIndex": 2,
    "type": 1,
    "showTip": "2个英雄升级到2级",
    "MissionType": 2,
    "UseNum": 2,
    "UseId": 2,
    "Mission": 108,
    "story1": "升级英雄，提升能力。",
    "story2": "恭喜你，实力又提升一步。",
    "sound1": "renwu_start_5",
    "sound2": "renwu_end_5",
    "Reward": "1:11:30|1:12:10000|1:22:2|1:10010:2"
  },
  {
    "id": 5,
    "nextid": 6,
    "uiIndex": 2,
    "type": 1,
    "showTip": "通关章节1-3",
    "MissionType": 1,
    "UseNum": 1,
    "UseId": 14,
    "Mission": 101,
    "story1": "勇闯难关，祝你一路顺风。",
    "story2": "太棒了，这一关你都轻松通过。",
    "sound1": "renwu_start_6",
    "sound2": "renwu_end_6",
    "Reward": "1:11:30|1:12:10000|1:22:2|1:10201:2"
  },
  {
    "id": 6,
    "nextid": 7,
    "uiIndex": 2,
    "type": 1,
    "showTip": "累计召唤10次",
    "MissionType": 8,
    "UseNum": 10,
    "UseId": 0,
    "Mission": 102,
    "story1": "前往获得新的伙伴。",
    "story2": "在你的英明一下，又一位强力英雄加入你的阵营了。",
    "sound1": "renwu_start_2",
    "sound2": "renwu_end_2",
    "Reward": "1:11:30|1:12:10000|1:22:2|1:10010:2"
  },
  {
    "id": 7,
    "nextid": 8,
    "uiIndex": 2,
    "type": 1,
    "showTip": "2个英雄升级到3级",
    "MissionType": 2,
    "UseNum": 2,
    "UseId": 3,
    "Mission": 108,
    "story1": "召唤英雄，获得新的伙伴。",
    "story2": "你获得了新的伙伴，后面的难关将更加轻松。",
    "sound1": "renwu_start_7",
    "sound2": "renwu_end_7",
    "Reward": "1:11:30|1:12:10000|1:22:2|1:10201:2"
  },
  {
    "id": 8,
    "nextid": 9,
    "uiIndex": 2,
    "type": 1,
    "showTip": "学习科技1次",
    "MissionType": 16,
    "UseNum": 1,
    "UseId": 0,
    "Mission": 116,
    "story1": "提升科技，强化能力",
    "story2": "这么快就领悟科技的力量，太棒了。",
    "sound1": "renwu_start_8",
    "sound2": "renwu_end_8",
    "Reward": "1:11:30|1:12:10000|1:22:2|1:10010:2"
  },
  {
    "id": 9,
    "nextid": 10,
    "uiIndex": 2,
    "type": 1,
    "showTip": "通关章节1-4",
    "MissionType": 1,
    "UseNum": 1,
    "UseId": 15,
    "Mission": 101,
    "story1": "勇闯难关，祝你一路顺风。",
    "story2": "太棒了，这一关你都轻松通过。",
    "sound1": "renwu_start_9",
    "sound2": "renwu_end_9",
    "Reward": "1:11:30|1:12:10000|1:22:2|1:10201:2"
  },
  {
    "id": 10,
    "nextid": 11,
    "uiIndex": 2,
    "type": 1,
    "showTip": "3个英雄升到4级",
    "MissionType": 2,
    "UseNum": 3,
    "UseId": 4,
    "Mission": 108,
    "story1": "英雄突破，实力提升。",
    "story2": "似乎发生了不一样的变化，好像更强了。",
    "sound1": "renwu_start_10",
    "sound2": "renwu_end_10",
    "Reward": "1:11:30|1:12:10000|1:22:2|1:10010:2"
  },
  {
    "id": 11,
    "nextid": 12,
    "uiIndex": 2,
    "type": 1,
    "showTip": "通关章节1-5",
    "MissionType": 1,
    "UseNum": 1,
    "UseId": 16,
    "Mission": 101,
    "story1": "勇闯难关，祝你一路顺风。",
    "story2": "太棒了，这一关你都轻松通过。",
    "sound1": "renwu_start_11",
    "sound2": "renwu_end_11",
    "Reward": "1:11:30|1:12:10000|1:22:2|1:10201:2"
  },
  {
    "id": 12,
    "nextid": 13,
    "uiIndex": 2,
    "type": 1,
    "showTip": "3个英雄升到5级",
    "MissionType": 2,
    "UseNum": 3,
    "UseId": 5,
    "Mission": 108,
    "story1": "合理搭配阵容，有利于顺利通关。",
    "story2": "完美的阵容搭配，任何难关都不在话下。",
    "sound1": "renwu_start_12",
    "sound2": "renwu_end_12",
    "Reward": "1:11:30|1:12:10000|1:22:2|1:10010:2"
  },
  {
    "id": 13,
    "nextid": 14,
    "uiIndex": 2,
    "type": 1,
    "showTip": "通关章节1-6",
    "MissionType": 1,
    "UseNum": 1,
    "UseId": 17,
    "Mission": 101,
    "story1": "勇闯难关，祝你一路顺风。",
    "story2": "太棒了，这一关你都轻松通过。",
    "sound1": "renwu_start_13",
    "sound2": "renwu_end_13",
    "Reward": "1:11:30|1:12:10000|1:22:2|1:10201:2"
  },
  {
    "id": 14,
    "nextid": 15,
    "uiIndex": 2,
    "type": 1,
    "showTip": "3个英雄升到6级",
    "MissionType": 2,
    "UseNum": 3,
    "UseId": 6,
    "Mission": 108,
    "story1": "升级英雄，提升能力。",
    "story2": "你的能力更上一层楼了，以后也要继续加油。",
    "sound1": "renwu_start_14",
    "sound2": "renwu_end_14",
    "Reward": "1:11:30|1:12:10000|1:22:2|1:10010:2"
  },
  {
    "id": 15,
    "nextid": 16,
    "uiIndex": 2,
    "type": 1,
    "showTip": "通关章节1-7",
    "MissionType": 1,
    "UseNum": 1,
    "UseId": 18,
    "Mission": 101,
    "story1": "勇闯难关，祝你一路顺风。",
    "story2": "太棒了，这一关你都轻松通过。",
    "sound1": "renwu_start_15",
    "sound2": "renwu_end_15",
    "Reward": "1:11:30|1:12:10000|1:22:2|1:10201:2"
  },
  {
    "id": 16,
    "nextid": 17,
    "uiIndex": 2,
    "type": 1,
    "showTip": "累计召唤10次",
    "MissionType": 8,
    "UseNum": 20,
    "UseId": 0,
    "Mission": 102,
    "story1": "全力拓建你的队伍。",
    "story2": "领导你的英雄们勇闯难关吧。",
    "sound1": "renwu_start_16",
    "sound2": "renwu_end_16",
    "Reward": "1:11:30|1:12:10000|1:22:2|1:10010:2"
  },
  {
    "id": 17,
    "nextid": 18,
    "uiIndex": 2,
    "type": 1,
    "showTip": "3个英雄升到7级",
    "MissionType": 2,
    "UseNum": 3,
    "UseId": 7,
    "Mission": 108,
    "story1": "一键升级，英雄属性快速提升",
    "story2": "你已经掌握英雄能力提升的关键了，希望你再接再厉。",
    "sound1": "renwu_start_17",
    "sound2": "renwu_end_17",
    "Reward": "1:11:30|1:12:10000|1:22:2|1:10201:2"
  },
  {
    "id": 18,
    "nextid": 19,
    "uiIndex": 2,
    "type": 1,
    "showTip": "通关章节1-8",
    "MissionType": 1,
    "UseNum": 1,
    "UseId": 21,
    "Mission": 101,
    "story1": "勇闯难关，祝你一路顺风。",
    "story2": "太棒了，这一关你都轻松通过。",
    "sound1": "renwu_start_18",
    "sound2": "renwu_end_18",
    "Reward": "1:11:30|1:12:10000|1:22:2|1:10010:2"
  },
  {
    "id": 19,
    "nextid": 20,
    "uiIndex": 2,
    "type": 1,
    "showTip": "3个英雄升到10级",
    "MissionType": 2,
    "UseNum": 3,
    "UseId": 10,
    "Mission": 108,
    "story1": "一键升级，英雄属性快速提升",
    "story2": "你已经掌握英雄能力提升的关键了，希望你再接再厉。",
    "sound1": "renwu_start_19",
    "sound2": "renwu_end_19",
    "Reward": "1:11:30|1:12:10000|1:22:2|1:10201:2"
  },
  {
    "id": 20,
    "nextid": 21,
    "uiIndex": 2,
    "type": 1,
    "showTip": "通关金币副本1次",
    "MissionType": 5,
    "UseNum": 1,
    "UseId": 0,
    "Mission": 117,
    "story1": "勇闯副本，金币副本可以给予你大量金币",
    "story2": "这一趟收获颇丰啊",
    "sound1": "renwu_start_19",
    "sound2": "renwu_end_19",
    "Reward": "1:11:30|1:12:10000|1:22:2|1:30006:1"
  },
  {
    "id": 21,
    "nextid": 22,
    "uiIndex": 2,
    "type": 1,
    "showTip": "英雄进阶1次",
    "MissionType": 15,
    "UseNum": 1,
    "UseId": 0,
    "Mission": 114,
    "story1": "英雄转职之路",
    "story2": "进阶英雄，你发现了新的力量，我就说还得是你。",
    "sound1": "renwu_start_19",
    "sound2": "renwu_end_19",
    "Reward": "1:11:30|1:12:10000|1:22:2|1:20002:10"
  },
  {
    "id": 22,
    "nextid": 23,
    "uiIndex": 2,
    "type": 1,
    "showTip": "通关科技副本1次",
    "MissionType": 6,
    "UseNum": 1,
    "UseId": 0,
    "Mission": 120,
    "story1": "科技副本可以提升士兵科技",
    "story2": "得到了这么多的材料，你的士兵又得到了强大的提升。",
    "sound1": "renwu_start_19",
    "sound2": "renwu_end_19",
    "Reward": "1:11:30|1:12:10000|1:22:2|1:20003:5"
  },
  {
    "id": 23,
    "nextid": 24,
    "uiIndex": 2,
    "type": 1,
    "showTip": "获得1件蓝色装备",
    "MissionType": 10,
    "UseNum": 1,
    "UseId": 2,
    "Mission": 126,
    "story1": "稀有的装备",
    "story2": "你的装备也太漂亮了，这么稀有的装备都被你得到了。",
    "sound1": "renwu_start_19",
    "sound2": "renwu_end_19",
    "Reward": "1:11:30|1:12:10000|1:22:2|1:10011:2"
  },
  {
    "id": 24,
    "nextid": 25,
    "uiIndex": 2,
    "type": 1,
    "showTip": "穿戴1件装备",
    "MissionType": 9,
    "UseNum": 1,
    "UseId": 0,
    "Mission": 112,
    "story1": "整装待发",
    "story2": "嗯，这身装备很合你身，我相信你能发挥出他们的最大实力。",
    "sound1": "renwu_start_19",
    "sound2": "renwu_end_19",
    "Reward": "1:11:30|1:12:10000|1:22:2|1:10012:2"
  },
  {
    "id": 25,
    "nextid": 26,
    "uiIndex": 2,
    "type": 1,
    "showTip": "通关装备副本1次",
    "MissionType": 7,
    "UseNum": 1,
    "UseId": 0,
    "Mission": 123,
    "story1": "装备副本可以获得强力的装备",
    "story2": "哇，这么漂亮的武器是在副本里面出的吗，你也太幸运了。",
    "sound1": "renwu_start_19",
    "sound2": "renwu_end_19",
    "Reward": "1:11:30|1:12:10000|1:22:2|1:10013:2"
  },
  {
    "id": 26,
    "nextid": 27,
    "uiIndex": 2,
    "type": 1,
    "showTip": "1个英雄达到3星",
    "MissionType": 3,
    "UseNum": 1,
    "UseId": 3,
    "Mission": 110,
    "story1": "英雄升星可大幅度提升英雄升级属性",
    "story2": "你的英雄们变的更强了",
    "sound1": "renwu_start_19",
    "sound2": "renwu_end_19",
    "Reward": "1:11:30|1:12:10000|1:22:2|1:30006:1"
  },
  {
    "id": 27,
    "nextid": 28,
    "uiIndex": 2,
    "type": 1,
    "showTip": "消耗100点体力",
    "MissionType": 12,
    "UseNum": 100,
    "UseId": 0,
    "Mission": 104,
    "story1": "磨砺自身",
    "story2": "没想到你这么快就完成了，看来有点小看你了。",
    "sound1": "renwu_start_19",
    "sound2": "renwu_end_19",
    "Reward": "1:11:30|1:12:10000|1:22:2|1:20002:10"
  },
  {
    "id": 28,
    "nextid": 29,
    "uiIndex": 2,
    "type": 1,
    "showTip": "英雄进阶3次",
    "MissionType": 15,
    "UseNum": 3,
    "UseId": 0,
    "Mission": 114,
    "story1": "英雄转职之路",
    "story2": "进阶英雄，你发现了新的力量，我就说还得是你。",
    "sound1": "renwu_start_19",
    "sound2": "renwu_end_19",
    "Reward": "1:11:30|1:12:10000|1:22:2|1:20003:5"
  },
  {
    "id": 29,
    "nextid": 30,
    "uiIndex": 2,
    "type": 1,
    "showTip": "获得2件蓝色装备",
    "MissionType": 10,
    "UseNum": 2,
    "UseId": 2,
    "Mission": 126,
    "story1": "稀有的装备",
    "story2": "你的装备也太漂亮了，这么稀有的装备都被你得到了。",
    "sound1": "renwu_start_19",
    "sound2": "renwu_end_19",
    "Reward": "1:11:30|1:12:10000|1:22:2|1:10011:2"
  },
  {
    "id": 30,
    "nextid": 31,
    "uiIndex": 2,
    "type": 1,
    "showTip": "穿戴2件装备",
    "MissionType": 9,
    "UseNum": 2,
    "UseId": 0,
    "Mission": 112,
    "story1": "整装待发",
    "story2": "嗯，这身装备很合你身，我相信你能发挥出他们的最大实力。",
    "sound1": "renwu_start_19",
    "sound2": "renwu_end_19",
    "Reward": "1:11:30|1:12:10000|1:22:2|1:10012:2"
  },
  {
    "id": 31,
    "nextid": 32,
    "uiIndex": 2,
    "type": 1,
    "showTip": "2个英雄达到3星",
    "MissionType": 3,
    "UseNum": 2,
    "UseId": 3,
    "Mission": 110,
    "story1": "英雄升星可大幅度提升英雄升级属性",
    "story2": "你的英雄们变的更强了",
    "sound1": "renwu_start_19",
    "sound2": "renwu_end_19",
    "Reward": "1:11:30|1:12:10000|1:22:2|1:10013:2"
  },
  {
    "id": 32,
    "nextid": 33,
    "uiIndex": 2,
    "type": 1,
    "showTip": "3个英雄升级至13级",
    "MissionType": 2,
    "UseNum": 3,
    "UseId": 13,
    "Mission": 108,
    "story1": "一键升级，英雄属性快速提升",
    "story2": "你已经掌握英雄能力提升的关键了，希望你再接再厉。",
    "sound1": "renwu_start_19",
    "sound2": "renwu_end_19",
    "Reward": "1:11:30|1:12:10000|1:22:2|1:30006:1"
  },
  {
    "id": 33,
    "nextid": 34,
    "uiIndex": 2,
    "type": 1,
    "showTip": "关卡星星累计获得24颗",
    "MissionType": 14,
    "UseNum": 24,
    "UseId": 0,
    "Mission": 106,
    "story1": "完美通关",
    "story2": "这么困难的敌人都被你完美的击败，希望你以后也如此。",
    "sound1": "renwu_start_19",
    "sound2": "renwu_end_19",
    "Reward": "1:11:30|1:12:10000|1:22:2|1:20002:10"
  },
  {
    "id": 34,
    "nextid": 35,
    "uiIndex": 2,
    "type": 1,
    "showTip": "通关章节2-5",
    "MissionType": 1,
    "UseNum": 1,
    "UseId": 26,
    "Mission": 101,
    "story1": "勇闯难关，祝你一路顺风。",
    "story2": "太棒了，这一关你都轻松通过。",
    "sound1": "renwu_start_19",
    "sound2": "renwu_end_19",
    "Reward": "1:11:30|1:12:10000|1:22:2|1:20003:5"
  },
  {
    "id": 35,
    "nextid": 36,
    "uiIndex": 2,
    "type": 1,
    "showTip": "英雄进阶5次",
    "MissionType": 15,
    "UseNum": 5,
    "UseId": 0,
    "Mission": 114,
    "story1": "英雄转职之路",
    "story2": "进阶英雄，你发现了新的力量，我就说还得是你。",
    "sound1": "renwu_start_19",
    "sound2": "renwu_end_19",
    "Reward": "1:11:30|1:12:10000|1:22:2|1:10011:2"
  },
  {
    "id": 36,
    "nextid": 37,
    "uiIndex": 2,
    "type": 1,
    "showTip": "获得4件蓝色装备",
    "MissionType": 10,
    "UseNum": 4,
    "UseId": 2,
    "Mission": 126,
    "story1": "稀有的装备",
    "story2": "你的装备也太漂亮了，这么稀有的装备都被你得到了。",
    "sound1": "renwu_start_19",
    "sound2": "renwu_end_19",
    "Reward": "1:11:30|1:12:10000|1:22:2|1:10012:2"
  },
  {
    "id": 37,
    "nextid": 38,
    "uiIndex": 2,
    "type": 1,
    "showTip": "穿戴4件装备",
    "MissionType": 9,
    "UseNum": 4,
    "UseId": 0,
    "Mission": 112,
    "story1": "整装待发",
    "story2": "嗯，这身装备很合你身，我相信你能发挥出他们的最大实力。",
    "sound1": "renwu_start_19",
    "sound2": "renwu_end_19",
    "Reward": "1:11:30|1:12:10000|1:22:2|1:10013:2"
  },
  {
    "id": 38,
    "nextid": 39,
    "uiIndex": 2,
    "type": 1,
    "showTip": "3个英雄达到3星",
    "MissionType": 3,
    "UseNum": 3,
    "UseId": 3,
    "Mission": 110,
    "story1": "英雄升星可大幅度提升英雄升级属性",
    "story2": "你的英雄们变的更强了",
    "sound1": "renwu_start_19",
    "sound2": "renwu_end_19",
    "Reward": "1:11:30|1:12:10000|1:22:2|1:30006:1"
  },
  {
    "id": 39,
    "nextid": 40,
    "uiIndex": 2,
    "type": 1,
    "showTip": "4个英雄升级至13级",
    "MissionType": 2,
    "UseNum": 4,
    "UseId": 13,
    "Mission": 108,
    "story1": "一键升级，英雄属性快速提升",
    "story2": "你已经掌握英雄能力提升的关键了，希望你再接再厉。",
    "sound1": "renwu_start_19",
    "sound2": "renwu_end_19",
    "Reward": "1:11:30|1:12:10000|1:22:2|1:20002:10"
  },
  {
    "id": 40,
    "nextid": 41,
    "uiIndex": 2,
    "type": 1,
    "showTip": "挑战关卡3次",
    "MissionType": 11,
    "UseNum": 3,
    "UseId": 0,
    "Mission": 602,
    "story1": "战术演习",
    "story2": "通过多次挑战来完善自身，看来你挺不错嘛。",
    "sound1": "renwu_start_19",
    "sound2": "renwu_end_19",
    "Reward": "1:11:30|1:12:10000|1:22:2|1:20003:5"
  },
  {
    "id": 41,
    "nextid": 42,
    "uiIndex": 2,
    "type": 1,
    "showTip": "通关章节2-8",
    "MissionType": 1,
    "UseNum": 1,
    "UseId": 31,
    "Mission": 101,
    "story1": "勇闯难关，祝你一路顺风。",
    "story2": "太棒了，这一关你都轻松通过。",
    "sound1": "renwu_start_19",
    "sound2": "renwu_end_19",
    "Reward": "1:11:30|1:12:10000|1:22:2|1:10011:2"
  },
  {
    "id": 42,
    "nextid": 43,
    "uiIndex": 2,
    "type": 1,
    "showTip": "英雄进阶8次",
    "MissionType": 15,
    "UseNum": 8,
    "UseId": 0,
    "Mission": 114,
    "story1": "英雄转职之路",
    "story2": "进阶英雄，你发现了新的力量，我就说还得是你。",
    "sound1": "renwu_start_19",
    "sound2": "renwu_end_19",
    "Reward": "1:11:30|1:12:10000|1:22:2|1:10012:2"
  },
  {
    "id": 43,
    "nextid": 44,
    "uiIndex": 2,
    "type": 1,
    "showTip": "获得1件紫色装备",
    "MissionType": 10,
    "UseNum": 1,
    "UseId": 3,
    "Mission": 127,
    "story1": "稀有的装备",
    "story2": "你的装备也太漂亮了，这么稀有的装备都被你得到了。",
    "sound1": "renwu_start_19",
    "sound2": "renwu_end_19",
    "Reward": "1:11:30|1:12:10000|1:22:2|1:10013:2"
  },
  {
    "id": 44,
    "nextid": 45,
    "uiIndex": 2,
    "type": 1,
    "showTip": "穿戴6件装备",
    "MissionType": 9,
    "UseNum": 6,
    "UseId": 0,
    "Mission": 112,
    "story1": "整装待发",
    "story2": "嗯，这身装备很合你身，我相信你能发挥出他们的最大实力。",
    "sound1": "renwu_start_19",
    "sound2": "renwu_end_19",
    "Reward": "1:11:30|1:12:10000|1:22:2|1:30006:1"
  },
  {
    "id": 45,
    "nextid": 46,
    "uiIndex": 2,
    "type": 1,
    "showTip": "1个英雄达到4星",
    "MissionType": 3,
    "UseNum": 1,
    "UseId": 4,
    "Mission": 110,
    "story1": "英雄升星可大幅度提升英雄升级属性",
    "story2": "你的英雄们变的更强了",
    "sound1": "renwu_start_19",
    "sound2": "renwu_end_19",
    "Reward": "1:11:30|1:12:10000|1:22:2|1:20002:10"
  },
  {
    "id": 46,
    "nextid": 47,
    "uiIndex": 2,
    "type": 1,
    "showTip": "关卡星星累计获得36颗",
    "MissionType": 14,
    "UseNum": 36,
    "UseId": 0,
    "Mission": 106,
    "story1": "完美通关",
    "story2": "这么困难的敌人都被你完美的击败，希望你以后也如此。",
    "sound1": "renwu_start_19",
    "sound2": "renwu_end_19",
    "Reward": "1:11:30|1:12:10000|1:22:2|1:20003:5"
  },
  {
    "id": 47,
    "nextid": 48,
    "uiIndex": 2,
    "type": 1,
    "showTip": "通关章节3-5",
    "MissionType": 1,
    "UseNum": 1,
    "UseId": 36,
    "Mission": 101,
    "story1": "勇闯难关，祝你一路顺风。",
    "story2": "太棒了，这一关你都轻松通过。",
    "sound1": "renwu_start_19",
    "sound2": "renwu_end_19",
    "Reward": "1:11:30|1:12:10000|1:22:2|1:10011:2"
  },
  {
    "id": 48,
    "nextid": 49,
    "uiIndex": 2,
    "type": 1,
    "showTip": "学习科技10次",
    "MissionType": 16,
    "UseNum": 10,
    "UseId": 0,
    "Mission": 116,
    "story1": "提升科技，强化能力",
    "story2": "这么快就领悟科技的力量，太棒了。",
    "sound1": "renwu_start_19",
    "sound2": "renwu_end_19",
    "Reward": "1:11:30|1:12:10000|1:22:2|1:10012:2"
  },
  {
    "id": 49,
    "nextid": 50,
    "uiIndex": 2,
    "type": 1,
    "showTip": "英雄进阶10次",
    "MissionType": 15,
    "UseNum": 10,
    "UseId": 0,
    "Mission": 114,
    "story1": "英雄转职之路",
    "story2": "进阶英雄，你发现了新的力量，我就说还得是你。",
    "sound1": "renwu_start_19",
    "sound2": "renwu_end_19",
    "Reward": "1:11:30|1:12:10000|1:22:2|1:10013:2"
  },
  {
    "id": 50,
    "nextid": 51,
    "uiIndex": 2,
    "type": 1,
    "showTip": "获得2件紫色装备",
    "MissionType": 10,
    "UseNum": 2,
    "UseId": 3,
    "Mission": 127,
    "story1": "稀有的装备",
    "story2": "你的装备也太漂亮了，这么稀有的装备都被你得到了。",
    "sound1": "renwu_start_19",
    "sound2": "renwu_end_19",
    "Reward": "1:11:30|1:12:10000|1:22:2|1:30006:1"
  },
  {
    "id": 51,
    "nextid": 52,
    "uiIndex": 2,
    "type": 1,
    "showTip": "穿戴8件装备",
    "MissionType": 9,
    "UseNum": 8,
    "UseId": 0,
    "Mission": 112,
    "story1": "整装待发",
    "story2": "嗯，这身装备很合你身，我相信你能发挥出他们的最大实力。",
    "sound1": "renwu_start_19",
    "sound2": "renwu_end_19",
    "Reward": "1:11:30|1:12:10000|1:22:2|1:20002:10"
  },
  {
    "id": 52,
    "nextid": 53,
    "uiIndex": 2,
    "type": 1,
    "showTip": "2个英雄达到4星",
    "MissionType": 3,
    "UseNum": 2,
    "UseId": 4,
    "Mission": 110,
    "story1": "英雄升星可大幅度提升英雄升级属性",
    "story2": "你的英雄们变的更强了",
    "sound1": "renwu_start_19",
    "sound2": "renwu_end_19",
    "Reward": "1:11:30|1:12:10000|1:22:2|1:20003:5"
  },
  {
    "id": 53,
    "nextid": 54,
    "uiIndex": 2,
    "type": 1,
    "showTip": "通关章节3-8",
    "MissionType": 1,
    "UseNum": 1,
    "UseId": 41,
    "Mission": 101,
    "story1": "勇闯难关，祝你一路顺风。",
    "story2": "太棒了，这一关你都轻松通过。",
    "sound1": "renwu_start_19",
    "sound2": "renwu_end_19",
    "Reward": "1:11:30|1:12:10000|1:22:2|1:10011:2"
  },
  {
    "id": 54,
    "nextid": 55,
    "uiIndex": 2,
    "type": 1,
    "showTip": "3个英雄升级至18级",
    "MissionType": 2,
    "UseNum": 3,
    "UseId": 18,
    "Mission": 108,
    "story1": "一键升级，英雄属性快速提升",
    "story2": "你已经掌握英雄能力提升的关键了，希望你再接再厉。",
    "sound1": "renwu_start_19",
    "sound2": "renwu_end_19",
    "Reward": "1:11:30|1:12:10000|1:22:2|1:10012:2"
  },
  {
    "id": 55,
    "nextid": 56,
    "uiIndex": 2,
    "type": 1,
    "showTip": "通关章节4-5",
    "MissionType": 1,
    "UseNum": 1,
    "UseId": 46,
    "Mission": 101,
    "story1": "勇闯难关，祝你一路顺风。",
    "story2": "太棒了，这一关你都轻松通过。",
    "sound1": "renwu_start_19",
    "sound2": "renwu_end_19",
    "Reward": "1:11:30|1:12:10000|1:22:2|1:10013:2"
  },
  {
    "id": 56,
    "nextid": 57,
    "uiIndex": 2,
    "type": 1,
    "showTip": "英雄进阶15次",
    "MissionType": 15,
    "UseNum": 15,
    "UseId": 0,
    "Mission": 114,
    "story1": "英雄转职之路",
    "story2": "进阶英雄，你发现了新的力量，我就说还得是你。",
    "sound1": "renwu_start_19",
    "sound2": "renwu_end_19",
    "Reward": "1:11:30|1:12:10000|1:22:2|1:30006:1"
  },
  {
    "id": 57,
    "nextid": 58,
    "uiIndex": 2,
    "type": 1,
    "showTip": "获得1件金色装备",
    "MissionType": 10,
    "UseNum": 1,
    "UseId": 4,
    "Mission": 128,
    "story1": "稀有的装备",
    "story2": "你的装备也太漂亮了，这么稀有的装备都被你得到了。",
    "sound1": "renwu_start_19",
    "sound2": "renwu_end_19",
    "Reward": "1:11:30|1:12:10000|1:22:2|1:20002:10"
  },
  {
    "id": 58,
    "nextid": 59,
    "uiIndex": 2,
    "type": 1,
    "showTip": "穿戴10件装备",
    "MissionType": 9,
    "UseNum": 10,
    "UseId": 0,
    "Mission": 112,
    "story1": "整装待发",
    "story2": "嗯，这身装备很合你身，我相信你能发挥出他们的最大实力。",
    "sound1": "renwu_start_19",
    "sound2": "renwu_end_19",
    "Reward": "1:11:30|1:12:10000|1:22:2|1:20003:5"
  },
  {
    "id": 59,
    "nextid": 60,
    "uiIndex": 2,
    "type": 1,
    "showTip": "3个英雄达到4星",
    "MissionType": 3,
    "UseNum": 3,
    "UseId": 4,
    "Mission": 110,
    "story1": "英雄升星可大幅度提升英雄升级属性",
    "story2": "你的英雄们变的更强了",
    "sound1": "renwu_start_19",
    "sound2": "renwu_end_19",
    "Reward": "1:11:30|1:12:10000|1:22:2|1:10011:2"
  }
]